blockcerts_merkletools/__init__.py
blockcerts_merkletools-1.0.4.dist-info/licenses/LICENSE
blockcerts_merkletools-1.0.4.dist-info/METADATA
blockcerts_merkletools-1.0.4.dist-info/WHEEL
blockcerts_merkletools-1.0.4.dist-info/top_level.txt
blockcerts_merkletools-1.0.4.dist-info/RECORD
