Metadata-Version: 2.4
Name: blockcerts-merkletools
Version: 1.0.4
Summary: Merkle Tools
Home-page: https://github.com/blockchain-certificates/blockcerts-pymerkletools
Author: Blockcerts
Author-email: info@blockcerts.org
License: MIT
Keywords: merkle tree,blockchain
Classifier: Intended Audience :: Developers
Classifier: Intended Audience :: Education
Classifier: Intended Audience :: Science/Research
Classifier: License :: OSI Approved :: MIT License
Classifier: Programming Language :: Python :: 3.10
Classifier: Topic :: Software Development :: Libraries
Classifier: Topic :: Software Development :: Libraries :: Python Modules
License-File: LICENSE
Requires-Dist: web3==6.20.4
Dynamic: author
Dynamic: author-email
Dynamic: classifier
Dynamic: description
Dynamic: description-content-type
Dynamic: home-page
Dynamic: keywords
Dynamic: license
Dynamic: license-file
Dynamic: requires-dist
Dynamic: summary
